ensemblrestpy/__init__.py
ensemblrestpy/grch37.py
ensemblrestpy-15.10.dist-info/licenses/LICENSE
ensemblrestpy-15.10.dist-info/METADATA
ensemblrestpy-15.10.dist-info/WHEEL
ensemblrestpy-15.10.dist-info/top_level.txt
ensemblrestpy-15.10.dist-info/RECORD
