Metadata-Version: 2.4
Name: ensemblrestpy
Version: 15.10
Summary: Python client for Ensembl REST API
Author-email: Liu Sun <sunliu@yxnu.edu.cn>
Project-URL: Homepage, https://github.com/liu-sun/ensemblrestpy
Project-URL: Issues, https://github.com/liu-sun/ensemblrestpy/issues
Classifier: Programming Language :: Python :: 3
Classifier: License :: OSI Approved :: MIT License
Classifier: Operating System :: OS Independent
Requires-Python: >=3.12
License-File: LICENSE
Dynamic: license-file
